{"code":200,"status":"OK","data":{"number":56,"name":"سُورَةُ الوَاقِعَةِ","englishName":"Al-Waaqia","englishNameTranslation":"The Inevitable","revelationType":"Meccan","numberOfAyahs":96,"ayahs":[{"number":4980,"text":"بِسۡمِ ٱللَّهِ ٱلرَّحۡمَـٰنِ ٱلرَّحِیمِ إِذَا وَقَعَتِ ٱلۡوَاقِعَةُ\n","numberInSurah":1,"juz":27,"manzil":7,"page":534,"ruku":469,"hizbQuarter":214,"sajda":false},{"number":4981,"text":"لَیۡسَ لِوَقۡعَتِهَا كَاذِبَةٌ\n","numberInSurah":2,"juz":27,"manzil":7,"page":534,"ruku":469,"hizbQuarter":214,"sajda":false},{"number":4982,"text":"خَافِضَةࣱ رَّافِعَةٌ\n","numberInSurah":3,"juz":27,"manzil":7,"page":534,"ruku":469,"hizbQuarter":214,"sajda":false},{"number":4983,"text":"إِذَا رُجَّتِ ٱلۡأَرۡضُ رَجࣰّا\n","numberInSurah":4,"juz":27,"manzil":7,"page":534,"ruku":469,"hizbQuarter":214,"sajda":false},{"number":4984,"text":"وَبُسَّتِ ٱلۡجِبَالُ بَسࣰّا\n","numberInSurah":5,"juz":27,"manzil":7,"page":534,"ruku":469,"hizbQuarter":214,"sajda":false},{"number":4985,"text":"فَكَانَتۡ هَبَاۤءࣰ مُّنۢبَثࣰّا\n","numberInSurah":6,"juz":27,"manzil":7,"page":534,"ruku":469,"hizbQuarter":214,"sajda":false},{"number":4986,"text":"وَكُنتُمۡ أَزۡوَ ٰ⁠جࣰا ثَلَـٰثَةࣰ\n","numberInSurah":7,"juz":27,"manzil":7,"page":534,"ruku":469,"hizbQuarter":214,"sajda":false},{"number":4987,"text":"فَأَصۡحَـٰبُ ٱلۡمَیۡمَنَةِ مَاۤ أَصۡحَـٰبُ ٱلۡمَیۡمَنَةِ\n","numberInSurah":8,"juz":27,"manzil":7,"page":534,"ruku":469,"hizbQuarter":214,"sajda":false},{"number":4988,"text":"وَأَصۡحَـٰبُ ٱلۡمَشۡـَٔمَةِ مَاۤ أَصۡحَـٰبُ ٱلۡمَشۡـَٔمَةِ\n","numberInSurah":9,"juz":27,"manzil":7,"page":534,"ruku":469,"hizbQuarter":214,"sajda":false},{"number":4989,"text":"وَٱلسَّـٰبِقُونَ ٱلسَّـٰبِقُونَ\n","numberInSurah":10,"juz":27,"manzil":7,"page":534,"ruku":469,"hizbQuarter":214,"sajda":false},{"number":4990,"text":"أُو۟لَـٰۤىِٕكَ ٱلۡمُقَرَّبُونَ\n","numberInSurah":11,"juz":27,"manzil":7,"page":534,"ruku":469,"hizbQuarter":214,"sajda":false},{"number":4991,"text":"فِی جَنَّـٰتِ ٱلنَّعِیمِ\n","numberInSurah":12,"juz":27,"manzil":7,"page":534,"ruku":469,"hizbQuarter":214,"sajda":false},{"number":4992,"text":"ثُلَّةࣱ مِّنَ ٱلۡأَوَّلِینَ\n","numberInSurah":13,"juz":27,"manzil":7,"page":534,"ruku":469,"hizbQuarter":214,"sajda":false},{"number":4993,"text":"وَقَلِیلࣱ مِّنَ ٱلۡـَٔاخِرِینَ\n","numberInSurah":14,"juz":27,"manzil":7,"page":534,"ruku":469,"hizbQuarter":214,"sajda":false},{"number":4994,"text":"عَلَىٰ سُرُرࣲ مَّوۡضُونَةࣲ\n","numberInSurah":15,"juz":27,"manzil":7,"page":534,"ruku":469,"hizbQuarter":214,"sajda":false},{"number":4995,"text":"مُّتَّكِـِٔینَ عَلَیۡهَا مُتَقَـٰبِلِینَ\n","numberInSurah":16,"juz":27,"manzil":7,"page":534,"ruku":469,"hizbQuarter":214,"sajda":false},{"number":4996,"text":"یَطُوفُ عَلَیۡهِمۡ وِلۡدَ ٰ⁠نࣱ مُّخَلَّدُونَ\n","numberInSurah":17,"juz":27,"manzil":7,"page":535,"ruku":469,"hizbQuarter":214,"sajda":false},{"number":4997,"text":"بِأَكۡوَابࣲ وَأَبَارِیقَ وَكَأۡسࣲ مِّن مَّعِینࣲ\n","numberInSurah":18,"juz":27,"manzil":7,"page":535,"ruku":469,"hizbQuarter":214,"sajda":false},{"number":4998,"text":"لَّا یُصَدَّعُونَ عَنۡهَا وَلَا یُنزِفُونَ\n","numberInSurah":19,"juz":27,"manzil":7,"page":535,"ruku":469,"hizbQuarter":214,"sajda":false},{"number":4999,"text":"وَفَـٰكِهَةࣲ مِّمَّا یَتَخَیَّرُونَ\n","numberInSurah":20,"juz":27,"manzil":7,"page":535,"ruku":469,"hizbQuarter":214,"sajda":false},{"number":5000,"text":"وَلَحۡمِ طَیۡرࣲ مِّمَّا یَشۡتَهُونَ\n","numberInSurah":21,"juz":27,"manzil":7,"page":535,"ruku":469,"hizbQuarter":214,"sajda":false},{"number":5001,"text":"وَحُورٌ عِینࣱ\n","numberInSurah":22,"juz":27,"manzil":7,"page":535,"ruku":469,"hizbQuarter":214,"sajda":false},{"number":5002,"text":"كَأَمۡثَـٰلِ ٱللُّؤۡلُوِٕ ٱلۡمَكۡنُونِ\n","numberInSurah":23,"juz":27,"manzil":7,"page":535,"ruku":469,"hizbQuarter":214,"sajda":false},{"number":5003,"text":"جَزَاۤءَۢ بِمَا كَانُوا۟ یَعۡمَلُونَ\n","numberInSurah":24,"juz":27,"manzil":7,"page":535,"ruku":469,"hizbQuarter":214,"sajda":false},{"number":5004,"text":"لَا یَسۡمَعُونَ فِیهَا لَغۡوࣰا وَلَا تَأۡثِیمًا\n","numberInSurah":25,"juz":27,"manzil":7,"page":535,"ruku":469,"hizbQuarter":214,"sajda":false},{"number":5005,"text":"إِلَّا قِیلࣰا سَلَـٰمࣰا سَلَـٰمࣰا\n","numberInSurah":26,"juz":27,"manzil":7,"page":535,"ruku":469,"hizbQuarter":214,"sajda":false},{"number":5006,"text":"وَأَصۡحَـٰبُ ٱلۡیَمِینِ مَاۤ أَصۡحَـٰبُ ٱلۡیَمِینِ\n","numberInSurah":27,"juz":27,"manzil":7,"page":535,"ruku":469,"hizbQuarter":214,"sajda":false},{"number":5007,"text":"فِی سِدۡرࣲ مَّخۡضُودࣲ\n","numberInSurah":28,"juz":27,"manzil":7,"page":535,"ruku":469,"hizbQuarter":214,"sajda":false},{"number":5008,"text":"وَطَلۡحࣲ مَّنضُودࣲ\n","numberInSurah":29,"juz":27,"manzil":7,"page":535,"ruku":469,"hizbQuarter":214,"sajda":false},{"number":5009,"text":"وَظِلࣲّ مَّمۡدُودࣲ\n","numberInSurah":30,"juz":27,"manzil":7,"page":535,"ruku":469,"hizbQuarter":214,"sajda":false},{"number":5010,"text":"وَمَاۤءࣲ مَّسۡكُوبࣲ\n","numberInSurah":31,"juz":27,"manzil":7,"page":535,"ruku":469,"hizbQuarter":214,"sajda":false},{"number":5011,"text":"وَفَـٰكِهَةࣲ كَثِیرَةࣲ\n","numberInSurah":32,"juz":27,"manzil":7,"page":535,"ruku":469,"hizbQuarter":214,"sajda":false},{"number":5012,"text":"لَّا مَقۡطُوعَةࣲ وَلَا مَمۡنُوعَةࣲ\n","numberInSurah":33,"juz":27,"manzil":7,"page":535,"ruku":469,"hizbQuarter":214,"sajda":false},{"number":5013,"text":"وَفُرُشࣲ مَّرۡفُوعَةٍ\n","numberInSurah":34,"juz":27,"manzil":7,"page":535,"ruku":469,"hizbQuarter":214,"sajda":false},{"number":5014,"text":"إِنَّاۤ أَنشَأۡنَـٰهُنَّ إِنشَاۤءࣰ\n","numberInSurah":35,"juz":27,"manzil":7,"page":535,"ruku":469,"hizbQuarter":214,"sajda":false},{"number":5015,"text":"فَجَعَلۡنَـٰهُنَّ أَبۡكَارًا\n","numberInSurah":36,"juz":27,"manzil":7,"page":535,"ruku":469,"hizbQuarter":214,"sajda":false},{"number":5016,"text":"عُرُبًا أَتۡرَابࣰا\n","numberInSurah":37,"juz":27,"manzil":7,"page":535,"ruku":469,"hizbQuarter":214,"sajda":false},{"number":5017,"text":"لِّأَصۡحَـٰبِ ٱلۡیَمِینِ\n","numberInSurah":38,"juz":27,"manzil":7,"page":535,"ruku":469,"hizbQuarter":214,"sajda":false},{"number":5018,"text":"ثُلَّةࣱ مِّنَ ٱلۡأَوَّلِینَ\n","numberInSurah":39,"juz":27,"manzil":7,"page":535,"ruku":470,"hizbQuarter":214,"sajda":false},{"number":5019,"text":"وَثُلَّةࣱ مِّنَ ٱلۡـَٔاخِرِینَ\n","numberInSurah":40,"juz":27,"manzil":7,"page":535,"ruku":470,"hizbQuarter":214,"sajda":false},{"number":5020,"text":"وَأَصۡحَـٰبُ ٱلشِّمَالِ مَاۤ أَصۡحَـٰبُ ٱلشِّمَالِ\n","numberInSurah":41,"juz":27,"manzil":7,"page":535,"ruku":470,"hizbQuarter":214,"sajda":false},{"number":5021,"text":"فِی سَمُومࣲ وَحَمِیمࣲ\n","numberInSurah":42,"juz":27,"manzil":7,"page":535,"ruku":470,"hizbQuarter":214,"sajda":false},{"number":5022,"text":"وَظِلࣲّ مِّن یَحۡمُومࣲ\n","numberInSurah":43,"juz":27,"manzil":7,"page":535,"ruku":470,"hizbQuarter":214,"sajda":false},{"number":5023,"text":"لَّا بَارِدࣲ وَلَا كَرِیمٍ\n","numberInSurah":44,"juz":27,"manzil":7,"page":535,"ruku":470,"hizbQuarter":214,"sajda":false},{"number":5024,"text":"إِنَّهُمۡ كَانُوا۟ قَبۡلَ ذَ ٰ⁠لِكَ مُتۡرَفِینَ\n","numberInSurah":45,"juz":27,"manzil":7,"page":535,"ruku":470,"hizbQuarter":214,"sajda":false},{"number":5025,"text":"وَكَانُوا۟ یُصِرُّونَ عَلَى ٱلۡحِنثِ ٱلۡعَظِیمِ\n","numberInSurah":46,"juz":27,"manzil":7,"page":535,"ruku":470,"hizbQuarter":214,"sajda":false},{"number":5026,"text":"وَكَانُوا۟ یَقُولُونَ أَىِٕذَا مِتۡنَا وَكُنَّا تُرَابࣰا وَعِظَـٰمًا أَءِنَّا لَمَبۡعُوثُونَ\n","numberInSurah":47,"juz":27,"manzil":7,"page":535,"ruku":470,"hizbQuarter":214,"sajda":false},{"number":5027,"text":"أَوَءَابَاۤؤُنَا ٱلۡأَوَّلُونَ\n","numberInSurah":48,"juz":27,"manzil":7,"page":535,"ruku":470,"hizbQuarter":214,"sajda":false},{"number":5028,"text":"قُلۡ إِنَّ ٱلۡأَوَّلِینَ وَٱلۡـَٔاخِرِینَ\n","numberInSurah":49,"juz":27,"manzil":7,"page":535,"ruku":470,"hizbQuarter":214,"sajda":false},{"number":5029,"text":"لَمَجۡمُوعُونَ إِلَىٰ مِیقَـٰتِ یَوۡمࣲ مَّعۡلُومࣲ\n","numberInSurah":50,"juz":27,"manzil":7,"page":535,"ruku":470,"hizbQuarter":214,"sajda":false},{"number":5030,"text":"ثُمَّ إِنَّكُمۡ أَیُّهَا ٱلضَّاۤلُّونَ ٱلۡمُكَذِّبُونَ\n","numberInSurah":51,"juz":27,"manzil":7,"page":536,"ruku":470,"hizbQuarter":214,"sajda":false},{"number":5031,"text":"لَـَٔاكِلُونَ مِن شَجَرࣲ مِّن زَقُّومࣲ\n","numberInSurah":52,"juz":27,"manzil":7,"page":536,"ruku":470,"hizbQuarter":214,"sajda":false},{"number":5032,"text":"فَمَالِـُٔونَ مِنۡهَا ٱلۡبُطُونَ\n","numberInSurah":53,"juz":27,"manzil":7,"page":536,"ruku":470,"hizbQuarter":214,"sajda":false},{"number":5033,"text":"فَشَـٰرِبُونَ عَلَیۡهِ مِنَ ٱلۡحَمِیمِ\n","numberInSurah":54,"juz":27,"manzil":7,"page":536,"ruku":470,"hizbQuarter":214,"sajda":false},{"number":5034,"text":"فَشَـٰرِبُونَ شُرۡبَ ٱلۡهِیمِ\n","numberInSurah":55,"juz":27,"manzil":7,"page":536,"ruku":470,"hizbQuarter":214,"sajda":false},{"number":5035,"text":"هَـٰذَا نُزُلُهُمۡ یَوۡمَ ٱلدِّینِ\n","numberInSurah":56,"juz":27,"manzil":7,"page":536,"ruku":470,"hizbQuarter":214,"sajda":false},{"number":5036,"text":"نَحۡنُ خَلَقۡنَـٰكُمۡ فَلَوۡلَا تُصَدِّقُونَ\n","numberInSurah":57,"juz":27,"manzil":7,"page":536,"ruku":470,"hizbQuarter":214,"sajda":false},{"number":5037,"text":"أَفَرَءَیۡتُم مَّا تُمۡنُونَ\n","numberInSurah":58,"juz":27,"manzil":7,"page":536,"ruku":470,"hizbQuarter":214,"sajda":false},{"number":5038,"text":"ءَأَنتُمۡ تَخۡلُقُونَهُۥۤ أَمۡ نَحۡنُ ٱلۡخَـٰلِقُونَ\n","numberInSurah":59,"juz":27,"manzil":7,"page":536,"ruku":470,"hizbQuarter":214,"sajda":false},{"number":5039,"text":"نَحۡنُ قَدَّرۡنَا بَیۡنَكُمُ ٱلۡمَوۡتَ وَمَا نَحۡنُ بِمَسۡبُوقِینَ\n","numberInSurah":60,"juz":27,"manzil":7,"page":536,"ruku":470,"hizbQuarter":214,"sajda":false},{"number":5040,"text":"عَلَىٰۤ أَن نُّبَدِّلَ أَمۡثَـٰلَكُمۡ وَنُنشِئَكُمۡ فِی مَا لَا تَعۡلَمُونَ\n","numberInSurah":61,"juz":27,"manzil":7,"page":536,"ruku":470,"hizbQuarter":214,"sajda":false},{"number":5041,"text":"وَلَقَدۡ عَلِمۡتُمُ ٱلنَّشۡأَةَ ٱلۡأُولَىٰ فَلَوۡلَا تَذَكَّرُونَ\n","numberInSurah":62,"juz":27,"manzil":7,"page":536,"ruku":470,"hizbQuarter":214,"sajda":false},{"number":5042,"text":"أَفَرَءَیۡتُم مَّا تَحۡرُثُونَ\n","numberInSurah":63,"juz":27,"manzil":7,"page":536,"ruku":470,"hizbQuarter":214,"sajda":false},{"number":5043,"text":"ءَأَنتُمۡ تَزۡرَعُونَهُۥۤ أَمۡ نَحۡنُ ٱلزَّ ٰ⁠رِعُونَ\n","numberInSurah":64,"juz":27,"manzil":7,"page":536,"ruku":470,"hizbQuarter":214,"sajda":false},{"number":5044,"text":"لَوۡ نَشَاۤءُ لَجَعَلۡنَـٰهُ حُطَـٰمࣰا فَظَلۡتُمۡ تَفَكَّهُونَ\n","numberInSurah":65,"juz":27,"manzil":7,"page":536,"ruku":470,"hizbQuarter":214,"sajda":false},{"number":5045,"text":"إِنَّا لَمُغۡرَمُونَ\n","numberInSurah":66,"juz":27,"manzil":7,"page":536,"ruku":470,"hizbQuarter":214,"sajda":false},{"number":5046,"text":"بَلۡ نَحۡنُ مَحۡرُومُونَ\n","numberInSurah":67,"juz":27,"manzil":7,"page":536,"ruku":470,"hizbQuarter":214,"sajda":false},{"number":5047,"text":"أَفَرَءَیۡتُمُ ٱلۡمَاۤءَ ٱلَّذِی تَشۡرَبُونَ\n","numberInSurah":68,"juz":27,"manzil":7,"page":536,"ruku":470,"hizbQuarter":214,"sajda":false},{"number":5048,"text":"ءَأَنتُمۡ أَنزَلۡتُمُوهُ مِنَ ٱلۡمُزۡنِ أَمۡ نَحۡنُ ٱلۡمُنزِلُونَ\n","numberInSurah":69,"juz":27,"manzil":7,"page":536,"ruku":470,"hizbQuarter":214,"sajda":false},{"number":5049,"text":"لَوۡ نَشَاۤءُ جَعَلۡنَـٰهُ أُجَاجࣰا فَلَوۡلَا تَشۡكُرُونَ\n","numberInSurah":70,"juz":27,"manzil":7,"page":536,"ruku":470,"hizbQuarter":214,"sajda":false},{"number":5050,"text":"أَفَرَءَیۡتُمُ ٱلنَّارَ ٱلَّتِی تُورُونَ\n","numberInSurah":71,"juz":27,"manzil":7,"page":536,"ruku":470,"hizbQuarter":214,"sajda":false},{"number":5051,"text":"ءَأَنتُمۡ أَنشَأۡتُمۡ شَجَرَتَهَاۤ أَمۡ نَحۡنُ ٱلۡمُنشِـُٔونَ\n","numberInSurah":72,"juz":27,"manzil":7,"page":536,"ruku":470,"hizbQuarter":214,"sajda":false},{"number":5052,"text":"نَحۡنُ جَعَلۡنَـٰهَا تَذۡكِرَةࣰ وَمَتَـٰعࣰا لِّلۡمُقۡوِینَ\n","numberInSurah":73,"juz":27,"manzil":7,"page":536,"ruku":470,"hizbQuarter":214,"sajda":false},{"number":5053,"text":"فَسَبِّحۡ بِٱسۡمِ رَبِّكَ ٱلۡعَظِیمِ\n","numberInSurah":74,"juz":27,"manzil":7,"page":536,"ruku":470,"hizbQuarter":214,"sajda":false},{"number":5054,"text":"۞ فَلَاۤ أُقۡسِمُ بِمَوَ ٰ⁠قِعِ ٱلنُّجُومِ\n","numberInSurah":75,"juz":27,"manzil":7,"page":536,"ruku":471,"hizbQuarter":215,"sajda":false},{"number":5055,"text":"وَإِنَّهُۥ لَقَسَمࣱ لَّوۡ تَعۡلَمُونَ عَظِیمٌ\n","numberInSurah":76,"juz":27,"manzil":7,"page":536,"ruku":471,"hizbQuarter":215,"sajda":false},{"number":5056,"text":"إِنَّهُۥ لَقُرۡءَانࣱ كَرِیمࣱ\n","numberInSurah":77,"juz":27,"manzil":7,"page":537,"ruku":471,"hizbQuarter":215,"sajda":false},{"number":5057,"text":"فِی كِتَـٰبࣲ مَّكۡنُونࣲ\n","numberInSurah":78,"juz":27,"manzil":7,"page":537,"ruku":471,"hizbQuarter":215,"sajda":false},{"number":5058,"text":"لَّا یَمَسُّهُۥۤ إِلَّا ٱلۡمُطَهَّرُونَ\n","numberInSurah":79,"juz":27,"manzil":7,"page":537,"ruku":471,"hizbQuarter":215,"sajda":false},{"number":5059,"text":"تَنزِیلࣱ مِّن رَّبِّ ٱلۡعَـٰلَمِینَ\n","numberInSurah":80,"juz":27,"manzil":7,"page":537,"ruku":471,"hizbQuarter":215,"sajda":false},{"number":5060,"text":"أَفَبِهَـٰذَا ٱلۡحَدِیثِ أَنتُم مُّدۡهِنُونَ\n","numberInSurah":81,"juz":27,"manzil":7,"page":537,"ruku":471,"hizbQuarter":215,"sajda":false},{"number":5061,"text":"وَتَجۡعَلُونَ رِزۡقَكُمۡ أَنَّكُمۡ تُكَذِّبُونَ\n","numberInSurah":82,"juz":27,"manzil":7,"page":537,"ruku":471,"hizbQuarter":215,"sajda":false},{"number":5062,"text":"فَلَوۡلَاۤ إِذَا بَلَغَتِ ٱلۡحُلۡقُومَ\n","numberInSurah":83,"juz":27,"manzil":7,"page":537,"ruku":471,"hizbQuarter":215,"sajda":false},{"number":5063,"text":"وَأَنتُمۡ حِینَىِٕذࣲ تَنظُرُونَ\n","numberInSurah":84,"juz":27,"manzil":7,"page":537,"ruku":471,"hizbQuarter":215,"sajda":false},{"number":5064,"text":"وَنَحۡنُ أَقۡرَبُ إِلَیۡهِ مِنكُمۡ وَلَـٰكِن لَّا تُبۡصِرُونَ\n","numberInSurah":85,"juz":27,"manzil":7,"page":537,"ruku":471,"hizbQuarter":215,"sajda":false},{"number":5065,"text":"فَلَوۡلَاۤ إِن كُنتُمۡ غَیۡرَ مَدِینِینَ\n","numberInSurah":86,"juz":27,"manzil":7,"page":537,"ruku":471,"hizbQuarter":215,"sajda":false},{"number":5066,"text":"تَرۡجِعُونَهَاۤ إِن كُنتُمۡ صَـٰدِقِینَ\n","numberInSurah":87,"juz":27,"manzil":7,"page":537,"ruku":471,"hizbQuarter":215,"sajda":false},{"number":5067,"text":"فَأَمَّاۤ إِن كَانَ مِنَ ٱلۡمُقَرَّبِینَ\n","numberInSurah":88,"juz":27,"manzil":7,"page":537,"ruku":471,"hizbQuarter":215,"sajda":false},{"number":5068,"text":"فَرَوۡحࣱ وَرَیۡحَانࣱ وَجَنَّتُ نَعِیمࣲ\n","numberInSurah":89,"juz":27,"manzil":7,"page":537,"ruku":471,"hizbQuarter":215,"sajda":false},{"number":5069,"text":"وَأَمَّاۤ إِن كَانَ مِنۡ أَصۡحَـٰبِ ٱلۡیَمِینِ\n","numberInSurah":90,"juz":27,"manzil":7,"page":537,"ruku":471,"hizbQuarter":215,"sajda":false},{"number":5070,"text":"فَسَلَـٰمࣱ لَّكَ مِنۡ أَصۡحَـٰبِ ٱلۡیَمِینِ\n","numberInSurah":91,"juz":27,"manzil":7,"page":537,"ruku":471,"hizbQuarter":215,"sajda":false},{"number":5071,"text":"وَأَمَّاۤ إِن كَانَ مِنَ ٱلۡمُكَذِّبِینَ ٱلضَّاۤلِّینَ\n","numberInSurah":92,"juz":27,"manzil":7,"page":537,"ruku":471,"hizbQuarter":215,"sajda":false},{"number":5072,"text":"فَنُزُلࣱ مِّنۡ حَمِیمࣲ\n","numberInSurah":93,"juz":27,"manzil":7,"page":537,"ruku":471,"hizbQuarter":215,"sajda":false},{"number":5073,"text":"وَتَصۡلِیَةُ جَحِیمٍ\n","numberInSurah":94,"juz":27,"manzil":7,"page":537,"ruku":471,"hizbQuarter":215,"sajda":false},{"number":5074,"text":"إِنَّ هَـٰذَا لَهُوَ حَقُّ ٱلۡیَقِینِ\n","numberInSurah":95,"juz":27,"manzil":7,"page":537,"ruku":471,"hizbQuarter":215,"sajda":false},{"number":5075,"text":"فَسَبِّحۡ بِٱسۡمِ رَبِّكَ ٱلۡعَظِیمِ\n","numberInSurah":96,"juz":27,"manzil":7,"page":537,"ruku":471,"hizbQuarter":215,"sajda":false}],"edition":{"identifier":"quran-uthmani-quran-academy","language":"ar","name":"القرآن الكريم برسم العثماني","englishName":"Modified Quran Uthmani Text from the Quran Academy to work with the Kitab font","format":"text","type":"quran","direction":"rtl"}}}